decko/__init__.py
decko/app.py
decko/decorators.py
decko/exp.py
decko/immutable.py
decko/helper/__init__.py
decko/helper/exceptions.py
decko/helper/util.py
decko/helper/validation.py
decko-0.0.3.0.dist-info/LICENSE
decko-0.0.3.0.dist-info/METADATA
decko-0.0.3.0.dist-info/WHEEL
decko-0.0.3.0.dist-info/top_level.txt
decko-0.0.3.0.dist-info/RECORD
