Metadata-Version: 2.1
Name: decko
Version: 0.0.3.0
Summary: A simple decorator based utility for helping with debugging
Home-page: https://github.com/JWLee89/decko
Author: Jay Lee
Author-email: ljay189@gmail.com
License: UNKNOWN
Project-URL: Bug Tracker, https://github.com/JWLee89/decko/issues
Platform: UNKNOWN
Classifier: Programming Language :: Python :: 3
Classifier: License :: OSI Approved :: MIT License
Classifier: Operating System :: OS Independent
Requires-Python: >=3.6
